parso/__init__.py
parso/_compatibility.py
parso/cache.py
parso/file_io.py
parso/grammar.py
parso/normalizer.py
parso/parser.py
parso/py.typed
parso/tree.py
parso/utils.py
parso/pgen2/__init__.py
parso/pgen2/generator.py
parso/pgen2/grammar_parser.py
parso/python/__init__.py
parso/python/diff.py
parso/python/errors.py
parso/python/grammar310.txt
parso/python/grammar36.txt
parso/python/grammar37.txt
parso/python/grammar38.txt
parso/python/grammar39.txt
parso/python/parser.py
parso/python/pep8.py
parso/python/prefix.py
parso/python/token.py
parso/python/tokenize.py
parso/python/tree.py
parso-0.8.0.dist-info/AUTHORS.txt
parso-0.8.0.dist-info/LICENSE.txt
parso-0.8.0.dist-info/METADATA
parso-0.8.0.dist-info/WHEEL
parso-0.8.0.dist-info/top_level.txt
parso-0.8.0.dist-info/RECORD
