Metadata-Version: 2.1
Name: parso
Version: 0.8.0
Summary: A Python Parser
Home-page: https://github.com/davidhalter/parso
Author: David Halter
Author-email: davidhalter88@gmail.com
Maintainer: David Halter
Maintainer-email: davidhalter88@gmail.com
License: MIT
Keywords: python parser parsing
Platform: any
Classifier: Development Status :: 4 - Beta
Classifier: Environment :: Plugins
Classifier: Intended Audience :: Developers
Classifier: License :: OSI Approved :: MIT License
Classifier: Operating System :: OS Independent
Classifier: Programming Language :: Python :: 3
Classifier: Programming Language :: Python :: 3.6
Classifier: Programming Language :: Python :: 3.7
Classifier: Programming Language :: Python :: 3.8
Classifier: Programming Language :: Python :: 3.9
Classifier: Topic :: Software Development :: Libraries :: Python Modules
Classifier: Topic :: Text Editors :: Integrated Development Environments (IDE)
Classifier: Topic :: Utilities
Classifier: Typing :: Typed
Requires-Python: >=3.6
Provides-Extra: qa
Provides-Extra: testing
